{
  "db_name": "PostgreSQL",
  "query": "\n            SELECT \n                u1.email AS from_email, \n                u2.email AS to_email, \n                uc.is_accepted\n            FROM user_connection uc\n            JOIN users u1 ON uc.from_id = u1.id\n            JOIN users u2 ON uc.to_id = u2.id\n            WHERE uc.from_id = $1 AND uc.is_accepted = false\n        ",
  "describe": {
    "columns": [
      {
        "ordinal": 0,
        "name": "from_email",
        "type_info": "Text"
      },
      {
        "ordinal": 1,
        "name": "to_email",
        "type_info": "Text"
      },
      {
        "ordinal": 2,
        "name": "is_accepted",
        "type_info": "Bool"
      }
    ],
    "parameters": {
      "Left": [
        "Uuid"
      ]
    },
    "nullable": [
      false,
      false,
      false
    ]
  },
  "hash": "8c7bac09ed75283302c950b47bb84364d4f90b590fe3eb6c2380d73185967330"
}
